pyudev_zero/__init__.py
pyudev_zero-0.1.0.dist-info/LICENSE
pyudev_zero-0.1.0.dist-info/METADATA
pyudev_zero-0.1.0.dist-info/WHEEL
pyudev_zero-0.1.0.dist-info/top_level.txt
pyudev_zero-0.1.0.dist-info/RECORD
