Metadata-Version: 2.1
Name: pyudev_zero
Version: 0.1.0
Summary: A pure Python implementation of libudev-zero
Author: Mo10
Project-URL: Homepage, https://github.com/mo10/pyudev-zero
Project-URL: Issues, https://github.com/mo10/pyudev-zero/issues
Classifier: Programming Language :: Python :: 3
Classifier: License :: OSI Approved :: MIT License
Classifier: Operating System :: OS Independent
Requires-Python: >=3.8
License-File: LICENSE
